.gitignore
CHANGELOG.md
LICENSE
README.rst
setup.py
sphinx_epytext/__init__.py
sphinx_epytext/process_docstring.py
sphinx_epytext.egg-info/PKG-INFO
sphinx_epytext.egg-info/SOURCES.txt
sphinx_epytext.egg-info/dependency_links.txt
sphinx_epytext.egg-info/requires.txt
sphinx_epytext.egg-info/top_level.txt